auto_coder_web/__init__.py
auto_coder_web/auto_coder_runner_wrapper.py
auto_coder_web/file_manager.py
auto_coder_web/init_project.py
auto_coder_web/json_file_storage.py
auto_coder_web/lang.py
auto_coder_web/proxy.py
auto_coder_web/terminal.py
auto_coder_web/types.py
auto_coder_web/version.py
auto_coder_web/agentic_message_parser/__init__.py
auto_coder_web/agentic_message_parser/message_parser.py
auto_coder_web/agentic_message_parser/tool_parsers.py
auto_coder_web/common_router/__init__.py
auto_coder_web/common_router/active_context_router.py
auto_coder_web/common_router/auto_coder_conf_router.py
auto_coder_web/common_router/chat_list_manager.py
auto_coder_web/common_router/chat_list_router.py
auto_coder_web/common_router/chat_session_manager.py
auto_coder_web/common_router/compiler_router.py
auto_coder_web/common_router/completions_router.py
auto_coder_web/common_router/file_group_router.py
auto_coder_web/common_router/file_router.py
auto_coder_web/common_router/filecacher.py
auto_coder_web/common_router/lib_router.py
auto_coder_web/common_router/model_router.py
auto_coder_web/expert_routers/__init__.py
auto_coder_web/expert_routers/history_router.py
auto_coder_web/routers/__init__.py
auto_coder_web/routers/auto_router.py
auto_coder_web/routers/chat_panels_router.py
auto_coder_web/routers/chat_router.py
auto_coder_web/routers/code_editor_tabs_router.py
auto_coder_web/routers/coding_router.py
auto_coder_web/routers/commit_router.py
auto_coder_web/routers/config_router.py
auto_coder_web/routers/direct_chat_router.py
auto_coder_web/routers/editable_preview_router.py
auto_coder_web/routers/file_command_router.py
auto_coder_web/routers/index_router.py
auto_coder_web/routers/mcp_router.py
auto_coder_web/routers/rag_router.py
auto_coder_web/routers/rules_router.py
auto_coder_web/routers/settings_router.py
auto_coder_web/routers/todo_router.py
auto_coder_web/routers/upload_router.py
auto_coder_web/web/bridge.js
auto_coder_web/web/favicon.ico
auto_coder_web/web/index.html
auto_coder_web-0.1.127.dist-info/METADATA
auto_coder_web-0.1.127.dist-info/WHEEL
auto_coder_web-0.1.127.dist-info/entry_points.txt
auto_coder_web-0.1.127.dist-info/top_level.txt
auto_coder_web-0.1.127.dist-info/RECORD
