Metadata-Version: 2.1
Name: auto_coder_web
Version: 0.1.127
Summary: auto-coder.web: A Python Project
Author: allwefantasy
Classifier: Programming Language :: Python :: 3.10
Classifier: Programming Language :: Python :: 3.11
Classifier: Programming Language :: Python :: 3.12
Requires-Dist: auto-coder >=0.1.399
Requires-Dist: aiofiles >=24.1.0
Requires-Dist: psutil
Requires-Dist: watchdog
Requires-Dist: sse-starlette
Requires-Dist: websockets
Requires-Dist: pyyaml
Requires-Dist: gitpython
Requires-Dist: filelock >=3.13.1
Requires-Dist: python-multipart
Requires-Dist: pywinpty ; sys_platform == "win32"
